jledru_maths/Maths.py
jledru_maths/__init__.py
jledru_maths-0.1.1.dist-info/WHEEL
jledru_maths-0.1.1.dist-info/METADATA
jledru_maths-0.1.1.dist-info/RECORD
