Metadata-Version: 2.1
Name: jledru-maths
Version: 0.1.1
Summary: Testing package deployment
Home-page: https://github.com/jledru/jledru_maths/releases/tag/v0.1.1
Author: Julien Ledru
Author-email: julien.ledru@hei.fr
Requires-Python: >=3.8,<4.0
Classifier: Programming Language :: Python :: 3
Classifier: Programming Language :: Python :: 3.10
Classifier: Programming Language :: Python :: 3.8
Classifier: Programming Language :: Python :: 3.9
Project-URL: Repository, https://github.com/jledru/jledru_maths/releases/tag/v0.1.1
